tests/__init__.py
tests/test_converter/__init__.py
tests/test_converter/test_converter.py
tests/test_trainer/__init__.py
tests/test_trainer/test_trainer.py
yaket/__init__.py
yaket/trainer.py
yaket/converter/__init__.py
yaket/converter/converter.py
yaket/schema/__init__.py
yaket/schema/schema.py
yaket-1.3.10.dist-info/LICENSE
yaket-1.3.10.dist-info/METADATA
yaket-1.3.10.dist-info/WHEEL
yaket-1.3.10.dist-info/top_level.txt
yaket-1.3.10.dist-info/RECORD
