Metadata-Version: 2.1
Name: yaket
Version: 1.3.10
Summary: YAML Keras Trainer for quick AI development
Author-email: Andrea Favia <andrea.favia@pm.me>
Project-URL: Source, https://gitlab.com/andreafavia/yaket
Classifier: Programming Language :: Python :: 3
Classifier: Operating System :: OS Independent
Requires-Python: >=3.7
License-File: LICENSE
Requires-Dist: pydantic (>=1.9.0)
Requires-Dist: mlflow (>=1.27.0)
Requires-Dist: tf2onnx (>=1.11)
Requires-Dist: psutil
Requires-Dist: mkdocs (>=1.1.2)
Requires-Dist: mkdocs-material (>=5.4.0)
Requires-Dist: mkdocstrings[python]
Provides-Extra: examples
Requires-Dist: jiwer ; extra == 'examples'
Requires-Dist: onnxruntime (>=1.12) ; extra == 'examples'
Provides-Extra: tensorflow
Requires-Dist: tensorflow (>=2.4.0) ; extra == 'tensorflow'
